post_request_task/__init__.py
post_request_task/task.py
post_request_task/tests.py
django_post_request_task-0.5.dist-info/AUTHORS
django_post_request_task-0.5.dist-info/LICENSE
django_post_request_task-0.5.dist-info/METADATA
django_post_request_task-0.5.dist-info/WHEEL
django_post_request_task-0.5.dist-info/top_level.txt
django_post_request_task-0.5.dist-info/RECORD
